LICENSE.txt
MANIFEST.in
README.rst
setup.py
django_zipkin/__init__.py
django_zipkin/api.py
django_zipkin/constants.py
django_zipkin/data_store.py
django_zipkin/defaults.py
django_zipkin/id_generator.py
django_zipkin/middleware.py
django_zipkin/models.py
django_zipkin/schema.py
django_zipkin/utils.py
django_zipkin/zipkin_data.py
django_zipkin.egg-info/PKG-INFO
django_zipkin.egg-info/SOURCES.txt
django_zipkin.egg-info/dependency_links.txt
django_zipkin.egg-info/requires.txt
django_zipkin.egg-info/top_level.txt
django_zipkin/_thrift/__init__.py
django_zipkin/_thrift/scribe/Scribe.py
django_zipkin/_thrift/scribe/__init__.py
django_zipkin/_thrift/scribe/constants.py
django_zipkin/_thrift/scribe/ttypes.py
django_zipkin/_thrift/zipkinCollector/ZipkinCollector.py
django_zipkin/_thrift/zipkinCollector/__init__.py
django_zipkin/_thrift/zipkinCollector/constants.py
django_zipkin/_thrift/zipkinCollector/ttypes.py
django_zipkin/_thrift/zipkinCore/__init__.py
django_zipkin/_thrift/zipkinCore/constants.py
django_zipkin/_thrift/zipkinCore/ttypes.py
django_zipkin/_thrift/zipkinDependencies/__init__.py
django_zipkin/_thrift/zipkinDependencies/constants.py
django_zipkin/_thrift/zipkinDependencies/ttypes.py
django_zipkin/_thrift/zipkinQuery/ZipkinQuery.py
django_zipkin/_thrift/zipkinQuery/__init__.py
django_zipkin/_thrift/zipkinQuery/constants.py
django_zipkin/_thrift/zipkinQuery/ttypes.py
django_zipkin/tests/__init__.py
django_zipkin/tests/helpers.py
django_zipkin/tests/test_api.py
django_zipkin/tests/test_data_store.py
django_zipkin/tests/test_id_generator.py
django_zipkin/tests/test_middleware.py
django_zipkin/tests/test_zipkin_data.py