Metadata-Version: 1.1
Name: django-zipkin
Version: 0.0.2
Summary: django-zipkin is a Django middleware and api for recording and sending messages to Zipkin
Home-page: https://github.com/prezi/django-zipkin
Author: Zoltan Nagy, Zsolt Dollenstein
Author-email: zoltan.nagy@prezi.com, zsolt.dollenstein@prezi.com
License: WTFPL License
Keywords: django zipkin middleware
Platform: any
Classifier: Development Status :: 4 - Beta
Classifier: Environment :: Web Environment
Classifier: Framework :: Django
Classifier: Intended Audience :: Developers
Classifier: License :: Freely Distributable
Classifier: Operating System :: OS Independent
Classifier: Programming Language :: Python
Classifier: Programming Language :: Python :: 2
Classifier: Programming Language :: Python :: 2.6
Classifier: Programming Language :: Python :: 2.7
Classifier: Topic :: Software Development :: Libraries :: Application Frameworks
Classifier: Topic :: Software Development :: Libraries :: Python Modules
